{
    "objects": [
        {
            "objNum": 0,
            "objId": 2938,
            "objDist": 7870,
            "angle": 784,
            "speed": 0,
            "objContour": {
                "x": 7.7092573242187500e+03,
                "y": 1.5824829101562500e+03
            }
        },
        {
            "objNum": 1,
            "objId": 263,
            "objDist": 2030,
            "angle": 595,
            "speed": 0,
            "objContour": {
                "x": 1.7491071777343750e+03,
                "y": 1.0303028564453125e+03
            }
        },
        {
            "objNum": 2,
            "objId": 1431,
            "objDist": 1263,
            "angle": 790,
            "speed": 0,
            "objContour": {
                "x": 1.2397951660156250e+03,
                "y": 2.4099171447753906e+02
            }
        },
        {
            "objNum": 3,
            "objId": 2699,
            "objDist": 2931,
            "angle": 513,
            "speed": 0,
            "objContour": {
                "x": 2.2874416503906250e+03,
                "y": 1.8325861816406250e+03
            }
        },
        {
            "objNum": 4,
            "objId": 701,
            "objDist": 2455,
            "angle": 549,
            "speed": 0,
            "objContour": {
                "x": 2.0085576171875000e+03,
                "y": 1.4116378173828125e+03
            }
        },
        {
            "objNum": 5,
            "objId": 1302,
            "objDist": 8763,
            "angle": 677,
            "speed": 0,
            "objContour": {
                "x": 8.1076127929687500e+03,
                "y": 3.3251740722656250e+03
            }
        },
        {
            "objNum": 6,
            "objId": 307,
            "objDist": 1162,
            "angle": 265,
            "speed": 0,
            "objContour": {
                "x": 5.1848187255859375e+02,
                "y": 1.0399136962890625e+03
            }
        },
        {
            "objNum": 7,
            "objId": 656,
            "objDist": 7094,
            "angle": 410,
            "speed": 0,
            "objContour": {
                "x": 4.6540830078125000e+03,
                "y": 5.3539096679687500e+03
            }
        },
        {
            "objNum": 8,
            "objId": 661,
            "objDist": 7606,
            "angle": 402,
            "speed": 0,
            "objContour": {
                "x": 4.9093510742187500e+03,
                "y": 5.8094326171875000e+03
            }
        },
        {
            "objNum": 9,
            "objId": 810,
            "objDist": 4751,
            "angle": 448,
            "speed": 0,
            "objContour": {
                "x": 3.3477172851562500e+03,
                "y": 3.3711704101562500e+03
            }
        },
        {
            "objNum": 10,
            "objId": 1220,
            "objDist": 6090,
            "angle": 436,
            "speed": 0,
            "objContour": {
                "x": 4.1997832031250000e+03,
                "y": 4.4102065429687500e+03
            }
        },
        {
            "objNum": 11,
            "objId": 1507,
            "objDist": 5403,
            "angle": 251,
            "speed": 0,
            "objContour": {
                "x": 2.2919494628906250e+03,
                "y": 4.8927880859375000e+03
            }
        },
        {
            "objNum": 12,
            "objId": 1702,
            "objDist": 988,
            "angle": 110,
            "speed": 0,
            "objContour": {
                "x": 1.8851928710937500e+02,
                "y": 9.6984765625000000e+02
            }
        },
        {
            "objNum": 13,
            "objId": 1910,
            "objDist": 3917,
            "angle": 291,
            "speed": 0,
            "objContour": {
                "x": 1.9049757080078125e+03,
                "y": 3.4225656738281250e+03
            }
        },
        {
            "objNum": 14,
            "objId": 2228,
            "objDist": 17958,
            "angle": 173,
            "speed": 0,
            "objContour": {
                "x": 5.3402583007812500e+03,
                "y": 1.7145593750000000e+04
            }
        }
    ]
}
