{
    "objects": [
        {
            "objNum": 0,
            "objId": 2938,
            "objDist": 7861,
            "angle": 803,
            "speed": 0,
            "objContour": {
                "x": 7.7486152343750000e+03,
                "y": 1.3244947509765625e+03
            }
        },
        {
            "objNum": 1,
            "objId": 263,
            "objDist": 2097,
            "angle": 596,
            "speed": 0,
            "objContour": {
                "x": 1.8086911621093750e+03,
                "y": 1.0611527099609375e+03
            }
        },
        {
            "objNum": 2,
            "objId": 2699,
            "objDist": 3038,
            "angle": 524,
            "speed": 0,
            "objContour": {
                "x": 2.4069760742187500e+03,
                "y": 1.8536209716796875e+03
            }
        },
        {
            "objNum": 3,
            "objId": 701,
            "objDist": 2526,
            "angle": 566,
            "speed": 0,
            "objContour": {
                "x": 2.1088256835937500e+03,
                "y": 1.3905142822265625e+03
            }
        },
        {
            "objNum": 4,
            "objId": 307,
            "objDist": 1060,
            "angle": 275,
            "speed": 0,
            "objContour": {
                "x": 4.8945355224609375e+02,
                "y": 9.4023150634765625e+02
            }
        },
        {
            "objNum": 5,
            "objId": 656,
            "objDist": 7024,
            "angle": 432,
            "speed": 0,
            "objContour": {
                "x": 4.8082587890625000e+03,
                "y": 5.1202753906250000e+03
            }
        },
        {
            "objNum": 6,
            "objId": 3100,
            "objDist": 3909,
            "angle": 274,
            "speed": 0,
            "objContour": {
                "x": 1.7989210205078125e+03,
                "y": 3.4704702148437500e+03
            }
        },
        {
            "objNum": 7,
            "objId": 3373,
            "objDist": 1339,
            "angle": 801,
            "speed": 0,
            "objContour": {
                "x": 1.3190614013671875e+03,
                "y": 2.3021301269531250e+02
            }
        },
        {
            "objNum": 8,
            "objId": 3932,
            "objDist": 6511,
            "angle": 405,
            "speed": 0,
            "objContour": {
                "x": 4.2285561523437500e+03,
                "y": 4.9510029296875000e+03
            }
        },
        {
            "objNum": 9,
            "objId": 161,
            "objDist": 7526,
            "angle": 411,
            "speed": 0,
            "objContour": {
                "x": 4.9474062500000000e+03,
                "y": 5.6713178710937500e+03
            }
        },
        {
            "objNum": 10,
            "objId": 624,
            "objDist": 4945,
            "angle": 288,
            "speed": 0,
            "objContour": {
                "x": 2.3822719726562500e+03,
                "y": 4.3333364257812500e+03
            }
        },
        {
            "objNum": 11,
            "objId": 823,
            "objDist": 8497,
            "angle": 262,
            "speed": 0,
            "objContour": {
                "x": 3.7514753417968750e+03,
                "y": 7.6240043945312500e+03
            }
        },
        {
            "objNum": 12,
            "objId": 1181,
            "objDist": 1002,
            "angle": 120,
            "speed": 0,
            "objContour": {
                "x": 2.0832751464843750e+02,
                "y": 9.8010388183593750e+02
            }
        }
    ]
}
